lupi_mfa/__init__.py
lupi_mfa/lupi_mfa.py
lupi_mfa-6.1.0.dist-info/LICENSE.txt
lupi_mfa-6.1.0.dist-info/METADATA
lupi_mfa-6.1.0.dist-info/WHEEL
lupi_mfa-6.1.0.dist-info/entry_points.txt
lupi_mfa-6.1.0.dist-info/top_level.txt
lupi_mfa-6.1.0.dist-info/RECORD
